compass_api_sdk/__init__.py
compass_api_sdk/_hooks/__init__.py
compass_api_sdk/_hooks/sdkhooks.py
compass_api_sdk/_hooks/types.py
compass_api_sdk/_version.py
compass_api_sdk/aave_v3.py
compass_api_sdk/aerodrome_slipstream.py
compass_api_sdk/basesdk.py
compass_api_sdk/erc_4626_vaults.py
compass_api_sdk/errors/__init__.py
compass_api_sdk/errors/apierror.py
compass_api_sdk/errors/compassapierror.py
compass_api_sdk/errors/httpvalidationerror.py
compass_api_sdk/errors/no_response_error.py
compass_api_sdk/errors/responsevalidationerror.py
compass_api_sdk/ethena.py
compass_api_sdk/httpclient.py
compass_api_sdk/models/__init__.py
compass_api_sdk/models/aaveavgrateresponse.py
compass_api_sdk/models/aaveborrowparams.py
compass_api_sdk/models/aaveborrowrequest.py
compass_api_sdk/models/aavehistoricaltransactionsresponse.py
compass_api_sdk/models/aaveliquiditychangeresponse.py
compass_api_sdk/models/aavelooprequest.py
compass_api_sdk/models/aaverateresponse.py
compass_api_sdk/models/aaverepayparams.py
compass_api_sdk/models/aaverepayrequest.py
compass_api_sdk/models/aavereserveoverviewresponse.py
compass_api_sdk/models/aavestdrateresponse.py
compass_api_sdk/models/aavesupplyparams.py
compass_api_sdk/models/aavesupplyrequest.py
compass_api_sdk/models/aavesupportedtokenmetadata.py
compass_api_sdk/models/aavesupportedtokensresponse.py
compass_api_sdk/models/aavetokenpriceresponse.py
compass_api_sdk/models/aaveuserpositionpertokenresponse.py
compass_api_sdk/models/aaveuserpositionsummaryresponse.py
compass_api_sdk/models/aavewithdrawparams.py
compass_api_sdk/models/aavewithdrawrequest.py
compass_api_sdk/models/aerodromelppositionsresponse.py
compass_api_sdk/models/aerodromeposition.py
compass_api_sdk/models/aerodromeslipstreambuyexactlyparams.py
compass_api_sdk/models/aerodromeslipstreambuyexactlyrequest.py
compass_api_sdk/models/aerodromeslipstreamincreaseliquidityprovisionparams.py
compass_api_sdk/models/aerodromeslipstreamincreaseliquidityprovisionrequest.py
speakeasy_testing_sdk-1.3.2.dist-info/METADATA
speakeasy_testing_sdk-1.3.2.dist-info/WHEEL
speakeasy_testing_sdk-1.3.2.dist-info/RECORD
